NSOQCNM/TocaFita.py
NSOQCNM/__init__.py
TocaFita-0.0.6.dist-info/LICENSE
TocaFita-0.0.6.dist-info/METADATA
TocaFita-0.0.6.dist-info/WHEEL
TocaFita-0.0.6.dist-info/top_level.txt
TocaFita-0.0.6.dist-info/RECORD
