Metadata-Version: 2.1
Name: TocaFita
Version: 0.0.6
Summary: Pacote que faz a reprodução de uma lista de musicas
Home-page: https://github.com/Bryan-martins/TocaFita.git
Author: Bryan Martins/Valderlandia Macedo
Author-email: ridangamer@gmail.com
License: UNKNOWN
Project-URL: Bug Tracker, https://github.com/Bryan-martins/TocaFita.git
Platform: UNKNOWN
Classifier: Programming Language :: Python :: 3
Classifier: License :: OSI Approved :: MIT License
Classifier: Operating System :: OS Independent
Requires-Python: >=3.8
License-File: LICENSE
